{"nodes": [{"id": "components_themescript_themescript", "label": "ThemeScript", "file_type": "code", "source_file": "frontend/components/ThemeScript.tsx", "source_location": "line 4", "source_url": null, "captured_at": null, "author": null, "contributor": null}, {"id": "concept_theme_persistence", "label": "Theme persistence via localStorage + data-theme attribute", "file_type": "rationale", "source_file": "frontend/components/ThemeScript.tsx", "source_location": null, "source_url": null, "captured_at": null, "author": null, "contributor": null}], "edges": [{"source": "concept_theme_persistence", "target": "components_themescript_themescript", "relation": "rationale_for", "confidence": "INFERRED", "confidence_score": 0.95, "source_file": "frontend/components/ThemeScript.tsx", "source_location": null, "weight": 1.0}], "hyperedges": []}